condatos/.ipynb_checkpoints/__init__-checkpoint.py
condatos/__init__.py
condatos-0.1.0.dist-info/METADATA
condatos-0.1.0.dist-info/WHEEL
condatos-0.1.0.dist-info/RECORD
