Metadata-Version: 2.1
Name: condatos
Version: 0.1.0
Summary: ejemplotaller
Author: Carolina Trogliero
Author-email: carolinatrogliero@gmail.com
Requires-Python: >=3.10,<4.0
Classifier: Programming Language :: Python :: 3
Classifier: Programming Language :: Python :: 3.10
Classifier: Programming Language :: Python :: 3.11
Classifier: Programming Language :: Python :: 3.12
Classifier: Programming Language :: Python :: 3.13
